playgolf/__init__.py
playgolf/playgolf.py
playgolf/playgolf_data.csv
playgolf/playgolf_test.csv
playgolf-0.8.dist-info/METADATA
playgolf-0.8.dist-info/WHEEL
playgolf-0.8.dist-info/top_level.txt
playgolf-0.8.dist-info/RECORD
